nccm/__init__.py
nccm/nccm.py
nccm-0.1.0.dist-info/LICENSE
nccm-0.1.0.dist-info/METADATA
nccm-0.1.0.dist-info/WHEEL
nccm-0.1.0.dist-info/top_level.txt
nccm-0.1.0.dist-info/RECORD
