Metadata-Version: 2.1
Name: nccm
Version: 0.1.0
Summary: NCurses ssh Connection Manager
Home-page: https://github.com/flyingrhinonz/nccm
Author: Kenneth Aaron
Author-email: flyingrhino@orcon.net.nz
License: GNU GPLv3
Platform: UNKNOWN
Classifier: Programming Language :: Python :: 3
Classifier: Development Status :: 4 - Beta
Classifier: License :: OSI Approved :: GNU General Public License v3 (GPLv3)
Classifier: Operating System :: POSIX :: Linux
Requires-Python: >=3.5
Requires-Dist: PyYaml
